.gitignore
CREDITS
HISTORY.rst
LICENSE
MANIFEST.in
Makefile
README.rst
make.bat
pyproject.toml
setup.py
demo/anti_flood_ftpd.py
demo/basic_ftpd.py
demo/keycert.pem
demo/md5_ftpd.py
demo/multi_proc_ftp.py
demo/multi_thread_ftp.py
demo/throttled_ftpd.py
demo/tls_ftpd.py
demo/unix_daemon.py
demo/unix_ftpd.py
demo/winnt_ftpd.py
docs/.readthedocs.yaml
docs/Makefile
docs/README
docs/adoptions.rst
docs/api.rst
docs/benchmarks.rst
docs/conf.py
docs/faqs.rst
docs/index.rst
docs/install.rst
docs/make.bat
docs/requirements.txt
docs/rfc-compliance.rst
docs/tutorial.rst
docs/images/freebsd.gif
pyftpdlib/__init__.py
pyftpdlib/__main__.py
pyftpdlib/authorizers.py
pyftpdlib/filesystems.py
pyftpdlib/handlers.py
pyftpdlib/ioloop.py
pyftpdlib/log.py
pyftpdlib/prefork.py
pyftpdlib/servers.py
pyftpdlib.egg-info/PKG-INFO
pyftpdlib.egg-info/SOURCES.txt
pyftpdlib.egg-info/dependency_links.txt
pyftpdlib.egg-info/requires.txt
pyftpdlib.egg-info/top_level.txt
pyftpdlib/test/README
pyftpdlib/test/__init__.py
pyftpdlib/test/conftest.py
pyftpdlib/test/keycert.pem
pyftpdlib/test/test_authorizers.py
pyftpdlib/test/test_cli.py
pyftpdlib/test/test_filesystems.py
pyftpdlib/test/test_functional.py
pyftpdlib/test/test_functional_ssl.py
pyftpdlib/test/test_ioloop.py
pyftpdlib/test/test_servers.py
scripts/ftpbench
scripts/internal/generate_manifest.py
scripts/internal/git_pre_commit.py
scripts/internal/print_announce.py
scripts/internal/purge_installation.py
scripts/internal/winmake.py